rawdisk/__init__.py
rawdisk/main.py
rawdisk/reader.py
rawdisk/filesystems/__init__.py
rawdisk/filesystems/detector.py
rawdisk/filesystems/unknown_volume.py
rawdisk/filesystems/volume.py
rawdisk/plugins/__init__.py
rawdisk/plugins/categories.py
rawdisk/plugins/manager.py
rawdisk/plugins/filesystems/__init__.py
rawdisk/plugins/filesystems/apple_boot.yapsy-plugin
rawdisk/plugins/filesystems/efi_system.yapsy-plugin
rawdisk/plugins/filesystems/hfs_plus.yapsy-plugin
rawdisk/plugins/filesystems/ntfs.yapsy-plugin
rawdisk/plugins/filesystems/apple_boot/__init__.py
rawdisk/plugins/filesystems/apple_boot/apple_boot.py
rawdisk/plugins/filesystems/apple_boot/apple_boot_volume.py
rawdisk/plugins/filesystems/efi_system/__init__.py
rawdisk/plugins/filesystems/efi_system/efi_system.py
rawdisk/plugins/filesystems/efi_system/efi_system_volume.py
rawdisk/plugins/filesystems/hfs_plus/__init__.py
rawdisk/plugins/filesystems/hfs_plus/hfs_plus.py
rawdisk/plugins/filesystems/hfs_plus/hfs_plus_volume.py
rawdisk/plugins/filesystems/ntfs/__init__.py
rawdisk/plugins/filesystems/ntfs/bootsector.py
rawdisk/plugins/filesystems/ntfs/headers.py
rawdisk/plugins/filesystems/ntfs/mft.py
rawdisk/plugins/filesystems/ntfs/mft_attr_header.py
rawdisk/plugins/filesystems/ntfs/mft_attribute.py
rawdisk/plugins/filesystems/ntfs/mft_entry.py
rawdisk/plugins/filesystems/ntfs/ntfs.py
rawdisk/plugins/filesystems/ntfs/ntfs_volume.py
rawdisk/scheme/__init__.py
rawdisk/scheme/common.py
rawdisk/scheme/gpt.py
rawdisk/scheme/headers.py
rawdisk/scheme/mbr.py
rawdisk/util/__init__.py
rawdisk/util/filesize.py
rawdisk/util/filetimes.py
rawdisk/util/rawstruct.py
rawdisk/util/singleton.py
rawdisk-0.2.1.dist-info/DESCRIPTION.rst
rawdisk-0.2.1.dist-info/METADATA
rawdisk-0.2.1.dist-info/RECORD
rawdisk-0.2.1.dist-info/WHEEL
rawdisk-0.2.1.dist-info/entry_points.txt
rawdisk-0.2.1.dist-info/metadata.json
rawdisk-0.2.1.dist-info/top_level.txt
