Metadata-Version: 2.0
Name: rawdisk
Version: 0.2.1
Summary: Experimental python code to explore different volume formats
Home-page: https://github.com/dariusbakunas/rawdisk
Author: Darius Bakunas-Milanowski
Author-email: bakunas@gmail.com
License: BSD
Keywords: rawdisk
Platform: UNKNOWN
Classifier: Development Status :: 2 - Pre-Alpha
Classifier: Intended Audience :: Developers
Classifier: License :: OSI Approved :: BSD License
Classifier: Natural Language :: English
Classifier: Programming Language :: Python :: 3.5
Requires-Dist: Yapsy (==1.11.223)
Requires-Dist: docutils (<0.13.1)
Requires-Dist: hexdump (==3.3)
Requires-Dist: mock (==2.0.0)
Requires-Dist: nose (>=1.0)
Requires-Dist: pyxdg (==0.25)
Requires-Dist: sphinxcontrib-napoleon (==0.6.1)
Requires-Dist: wheel (==0.29.0)
